dash_fluentui_components/Badge.py
dash_fluentui_components/Button.py
dash_fluentui_components/Card.py
dash_fluentui_components/Checkbox.py
dash_fluentui_components/ComboBox.py
dash_fluentui_components/CompoundButton.py
dash_fluentui_components/CounterBadge.py
dash_fluentui_components/Dialog.py
dash_fluentui_components/Divider.py
dash_fluentui_components/Dropdown.py
dash_fluentui_components/FluentProvider.py
dash_fluentui_components/Input.py
dash_fluentui_components/Label.py
dash_fluentui_components/Page.py
dash_fluentui_components/PagesWithSidebar.py
dash_fluentui_components/RadioGroup.py
dash_fluentui_components/Slider.py
dash_fluentui_components/Switch.py
dash_fluentui_components/Tab.py
dash_fluentui_components/TabList.py
dash_fluentui_components/TabbedPages.py
dash_fluentui_components/Text.py
dash_fluentui_components/Textarea.py
dash_fluentui_components/ToggleButton.py
dash_fluentui_components/__init__.py
dash_fluentui_components/_imports_.py
dash_fluentui_components/dash_fluentui_components.min.js
dash_fluentui_components/metadata.json
dash_fluentui_components/package-info.json
package.json
dash_fluentui_components-0.1.0.dist-info/LICENSE
dash_fluentui_components-0.1.0.dist-info/METADATA
dash_fluentui_components-0.1.0.dist-info/WHEEL
dash_fluentui_components-0.1.0.dist-info/RECORD
