Metadata-Version: 2.1
Name: dash-fluentui-components
Version: 0.1.0
Summary: FluentUI components for Plotly Dash.
Home-page: https://github.com/roeap/dash-fluentui-components
License: MIT
Author: Robert Pack
Author-email: robstar.pack@gmail.com
Requires-Python: >=3.7,<4.0
Classifier: Framework :: Dash
Classifier: License :: OSI Approved :: MIT License
Classifier: Programming Language :: Python :: 3
Classifier: Programming Language :: Python :: 3.7
Classifier: Programming Language :: Python :: 3.8
Classifier: Programming Language :: Python :: 3.9
Classifier: Programming Language :: Python :: 3.10
Classifier: Programming Language :: Python :: 3.11
Requires-Dist: importlib-metadata (>=1.7.0) ; python_version < "3.8"
Project-URL: Repository, https://github.com/roeap/dash-fluentui-components
